_fastasr.cp310-win_amd64.pyd
libopenblas.dll
fastasr/__init__.py
fastasr-0.0.4.dist-info/LICENSE
fastasr-0.0.4.dist-info/METADATA
fastasr-0.0.4.dist-info/WHEEL
fastasr-0.0.4.dist-info/top_level.txt
fastasr-0.0.4.dist-info/RECORD
