Metadata-Version: 2.1
Name: fastasr
Version: 0.0.4
Summary: FastASR
Home-page: https://github.com/chenkui164/FastASR
License: Apache-2.0
Platform: UNKNOWN
Requires-Python: >=3.6
License-File: LICENSE
